tangerine/__init__.py
tangerine/bot.py
tangerine/scheduler.py
slack_tangerine-5.1.0.dist-info/LICENSE
slack_tangerine-5.1.0.dist-info/METADATA
slack_tangerine-5.1.0.dist-info/WHEEL
slack_tangerine-5.1.0.dist-info/top_level.txt
slack_tangerine-5.1.0.dist-info/zip-safe
slack_tangerine-5.1.0.dist-info/RECORD
