Metadata-Version: 2.1
Name: slack-tangerine
Version: 5.1.0
Summary: tangerine is a lightweight Slackbot framework that abstracts away all the boilerplate code required to write bots, allowing you to focus on the problem at hand.
Home-page: https://github.com/nficano/tangerine
Author: Nick Ficano
Author-email: nficano@gmail.com
License: MIT
Platform: UNKNOWN
Classifier: License :: OSI Approved :: MIT License
Classifier: Programming Language :: Python
Classifier: Programming Language :: Python :: 2.7
Classifier: Programming Language :: Python :: 3
Classifier: Programming Language :: Python :: 3.4
Classifier: Programming Language :: Python :: 3.5
Classifier: Programming Language :: Python :: 3.6
Classifier: Programming Language :: Python :: 3.7
Classifier: Programming Language :: Python :: Implementation :: CPython
Classifier: Programming Language :: Python :: Implementation :: PyPy
